opencensus/__init__.py
opencensus/proto/__init__.py
opencensus/proto/agent/__init__.py
opencensus/proto/agent/common/__init__.py
opencensus/proto/agent/common/v1/__init__.py
opencensus/proto/agent/common/v1/common_pb2.py
opencensus/proto/agent/metrics/__init__.py
opencensus/proto/agent/metrics/v1/__init__.py
opencensus/proto/agent/metrics/v1/metrics_service_pb2.py
opencensus/proto/agent/metrics/v1/metrics_service_pb2_grpc.py
opencensus/proto/agent/trace/__init__.py
opencensus/proto/agent/trace/v1/__init__.py
opencensus/proto/agent/trace/v1/trace_service_pb2.py
opencensus/proto/agent/trace/v1/trace_service_pb2_grpc.py
opencensus/proto/metrics/__init__.py
opencensus/proto/metrics/v1/__init__.py
opencensus/proto/metrics/v1/metrics_pb2.py
opencensus/proto/resource/__init__.py
opencensus/proto/resource/v1/__init__.py
opencensus/proto/resource/v1/resource_pb2.py
opencensus/proto/stats/__init__.py
opencensus/proto/stats/v1/__init__.py
opencensus/proto/stats/v1/stats_pb2.py
opencensus/proto/trace/__init__.py
opencensus/proto/trace/v1/__init__.py
opencensus/proto/trace/v1/trace_config_pb2.py
opencensus/proto/trace/v1/trace_pb2.py
opencensus_proto-0.1.0.dist-info/METADATA
opencensus_proto-0.1.0.dist-info/WHEEL
opencensus_proto-0.1.0.dist-info/namespace_packages.txt
opencensus_proto-0.1.0.dist-info/top_level.txt
opencensus_proto-0.1.0.dist-info/RECORD
